tmplr/__init__.py
tmplr/temple.py
tmplr/cli/__init__.py
tmplr/cli/editor.py
tmplr/cli/temples.py
tmplr/cli/tmplr.py
tmplr-0.4.0.dist-info/entry_points.txt
tmplr-0.4.0.dist-info/LICENSE
tmplr-0.4.0.dist-info/WHEEL
tmplr-0.4.0.dist-info/METADATA
tmplr-0.4.0.dist-info/RECORD
