Metadata-Version: 2.1
Name: tmplr
Version: 0.4.0
Summary: The holiest cli template system
Author-email: "D. Ben Knoble" <ben.knoble@gmail.com>
Requires-Python: >=3
Classifier: Development Status :: 3 - Alpha
Classifier: Intended Audience :: Developers
Classifier: Environment :: Console
Classifier: Topic :: Software Development :: Code Generators
Classifier: License :: OSI Approved :: MIT License
Classifier: Programming Language :: Python :: 3
Project-URL: GitHub, https://github.com/benknoble/tmplr
